{
  "2024_01_01_1": {
    "authors": [
      "Ross Whiteford",
      "Oscar Branson",
      "Dennis Mayk"
    ],
    "title": "Using Kgen to Generate Cross-Verified Apparent Equilibrium Constants (K∗) for Seawater Carbonate Chemistry",
    "journal": "Preprint",
    "doi": "10.22541/essoar.170421455.50048580/v1",
    "url": "https://doi.org/10.22541/essoar.170421455.50048580/v1"
  },
  "2024_07_08_1": {
    "authors": [
      "Oscar Branson",
      "Joji Uchikawa",
      "Madeleine S Bohlin",
      "Sambuddha Misra"
    ],
    "title": "Controls on Li partitioning and isotopic fractionation in inorganic calcite",
    "journal": "Geochimica et Cosmochimica Acta",
    "doi": "10.1016/j.gca.2024.07.001",
    "url": "https://doi.org/10.1016/j.gca.2024.07.001"
  }
}